ecotracker/__init__.py
ecotracker/data.py
ecotracker/meter.py
ecotracker/py.typed
ecotracker-0.1.15.dist-info/licenses/LICENSE
tests/__init__.py
tests/test_meter.py
ecotracker-0.1.15.dist-info/METADATA
ecotracker-0.1.15.dist-info/WHEEL
ecotracker-0.1.15.dist-info/top_level.txt
ecotracker-0.1.15.dist-info/RECORD
