Metadata-Version: 2.4
Name: ecotracker
Version: 0.1.15
Summary: A library for reading EcoTracker energy consumption data from everHome's local HTTP endpoint
Home-page: https://github.com/username/ecotracker
Author: Fabian
Author-email: everHome <info@everhome.cloud>
License: MIT
Project-URL: Homepage, https://github.com/everhome-gmbh/ecotracker
Project-URL: Bug Tracker, https://github.com/everhome-gmbh/ecotracker/issues
Classifier: Programming Language :: Python :: 3
Classifier: License :: OSI Approved :: MIT License
Classifier: Operating System :: OS Independent
Requires-Python: >=3.6
License-File: LICENSE
Requires-Dist: requests>=2.25.0
Dynamic: author
Dynamic: home-page
Dynamic: license-file
Dynamic: requires-python
